gclassifier/__init__.py
gclassifier/algo_model.model
gclassifier/classifier.py
gclassifier-0.6.dist-info/LICENSE
gclassifier-0.6.dist-info/METADATA
gclassifier-0.6.dist-info/WHEEL
gclassifier-0.6.dist-info/top_level.txt
gclassifier-0.6.dist-info/RECORD
