Metadata-Version: 2.1
Name: gclassifier
Version: 0.6
Summary: Gender classifier module for python
Home-page: https://github.com/dipghoshraj/Gender-classifer-module
Author: Dip Ghosh
Author-email: dipghoshraj@gmail.com
License: UNKNOWN
Platform: UNKNOWN
Classifier: Programming Language :: Python :: 3
Classifier: License :: OSI Approved :: MIT License
Classifier: Operating System :: OS Independent
Requires-Dist: cvlib (==0.2.6)
Requires-Dist: numpy (==1.19.5)
Requires-Dist: opencv-python (==4.5.1.48)
Requires-Dist: scipy (==1.6.1)
Requires-Dist: tensorflow (==2.4.1)
